django_logger_auth/__init__.py
django_logger_auth/admin.py
django_logger_auth/apps.py
django_logger_auth/config.py
django_logger_auth/models.py
django_logger_auth/signals.py
django_logger_auth/tests.py
django_logger_auth/utils.py
django_logger_auth/views.py
django_logger_auth/migrations/0001_initial.py
django_logger_auth/migrations/__init__.py
django_logger_auth-1.1.0.dist-info/licenses/LICENSE
django_logger_auth-1.1.0.dist-info/METADATA
django_logger_auth-1.1.0.dist-info/WHEEL
django_logger_auth-1.1.0.dist-info/top_level.txt
django_logger_auth-1.1.0.dist-info/RECORD
