Metadata-Version: 2.4
Name: django-logger-auth
Version: 1.1.0
Summary: Django application for logging authentication events (login/logout/failed) in the admin panel. Logs are stored in the database, with the option to save them to a file and output them to the console.
Author-email: devops-regulus <devopsregul@gmail.com>
License: MIT
Project-URL: Homepage, https://github.com/devops-regulus/django-logger-auth
Project-URL: Documentation, https://github.com/devops-regulus/django-logger-auth#readme
Project-URL: Repository, https://github.com/devops-regulus/django-logger-auth
Project-URL: Issues, https://github.com/devops-regulus/django-logger-auth/issues
Keywords: django,logger,authentication,authorization,login,security,logging,audit,middleware,signals,auth-events,django-logging,django-auth
Classifier: Development Status :: 5 - Production/Stable
Classifier: Environment :: Web Environment
Classifier: Framework :: Django
Classifier: Framework :: Django :: 5.0
Classifier: Programming Language :: Python :: 3
Classifier: Programming Language :: Python :: 3.10
Classifier: Programming Language :: Python :: 3.11
Classifier: Programming Language :: Python :: 3.12
Classifier: Programming Language :: Python :: 3.13
Classifier: Programming Language :: Python :: 3.14
Classifier: License :: OSI Approved :: MIT License
Classifier: Operating System :: OS Independent
Classifier: Intended Audience :: Developers
Classifier: Topic :: Software Development :: Libraries :: Python Modules
Requires-Python: <4,>=3.10
License-File: LICENSE
Requires-Dist: Django>=5.0
Requires-Dist: ipwhois>=1.3.0
Requires-Dist: requests>=2.32.5
Requires-Dist: pytz>=2025.2
Dynamic: license-file
